BERTSimilar/BERTSimilar.py
BERTSimilar/__init__.py
BERTSimilarWords/BERTSimilarWords.py
BERTSimilarWords/__init__.py
BERTSimilar-0.2.3.dist-info/LICENSE.txt
BERTSimilar-0.2.3.dist-info/METADATA
BERTSimilar-0.2.3.dist-info/WHEEL
BERTSimilar-0.2.3.dist-info/top_level.txt
BERTSimilar-0.2.3.dist-info/RECORD
